scoreganizer_client_lib/__init__.py
scoreganizer_client_lib/_version.py
scoreganizer_client_lib/api_token.py
scoreganizer_client_lib/exceptions.py
scoreganizer_client_lib/score.py
scoreganizer_client_lib/scoreganizer.py
scoreganizer_client_lib/tournament.py
scoreganizer_client_lib/version.py
scoreganizer_client_lib-0.3.1.dist-info/licenses/LICENSE.txt
scoreganizer_client_lib-0.3.1.dist-info/METADATA
scoreganizer_client_lib-0.3.1.dist-info/WHEEL
scoreganizer_client_lib-0.3.1.dist-info/top_level.txt
scoreganizer_client_lib-0.3.1.dist-info/RECORD
